starbridge/__init__.py
starbridge/cli.py
starbridge/service.py
starbridge/atlassian/__init__.py
starbridge/atlassian/settings.py
starbridge/claude/__init__.py
starbridge/claude/cli.py
starbridge/claude/service.py
starbridge/claude/util.py
starbridge/confluence/__init__.py
starbridge/confluence/cli.py
starbridge/confluence/service.py
starbridge/hello/__init__.py
starbridge/hello/cli.py
starbridge/hello/service.py
starbridge/instrumentation/__init__.py
starbridge/instrumentation/logfire.py
starbridge/instrumentation/otel_mcp_instrumentation.py
starbridge/mcp/__init__.py
starbridge/mcp/cli.py
starbridge/mcp/context.py
starbridge/mcp/decorators.py
starbridge/mcp/models.py
starbridge/mcp/server.py
starbridge/mcp/service.py
starbridge/search/__init__.py
starbridge/search/cli.py
starbridge/search/service.py
starbridge/search/settings.py
starbridge/utils/__init__.py
starbridge/utils/cli.py
starbridge/utils/console.py
starbridge/utils/di.py
starbridge/utils/health.py
starbridge/utils/logging.py
starbridge/utils/platform.py
starbridge/utils/settings.py
starbridge/utils/signature.py
starbridge/web/__init__.py
starbridge/web/cli.py
starbridge/web/models.py
starbridge/web/service.py
starbridge/web/settings.py
starbridge/web/utils.py
starbridge-0.10.12.dist-info/METADATA
starbridge-0.10.12.dist-info/WHEEL
starbridge-0.10.12.dist-info/entry_points.txt
starbridge-0.10.12.dist-info/licenses/LICENSE
starbridge-0.10.12.dist-info/RECORD
