Metadata-Version: 2.4
Name: starbridge
Version: 0.10.12
Summary: ⭐ Integrates Claude Desktop with the web, Google and Atlassian workspaces.
Project-URL: Homepage, https://starbridge.readthedocs.io/en/latest/
Project-URL: Documentation, https://starbridge.readthedocs.io/en/latest/
Project-URL: Source, https://github.com/helmut-hoffer-von-ankershoffen/starbridge
Project-URL: Changelog, https://github.com/helmut-hoffer-von-ankershoffen/starbridge/releases
Project-URL: Issues, https://github.com/helmut-hoffer-von-ankershoffen/starbridge/issues
Author-email: Helmut Hoffer von Ankershoffen <helmuthva@googlemail.com>
License: MIT License
License-File: LICENSE
Keywords: anthropic,atlassian,bump-my-version,claude,codecov,confluence,cyclonedx,devcontainer,docker,docker-compose,git-cliff,github-actions,google-drive,jira,logfire,mcp,nox,opentelemetry,pre-commit,pydantic,pytest,pytest-asyncio,pytest-cov,pytest-docker,pytest-env,pytest-xdist,renovate,ruff,sonarqube,typer,uv
Classifier: Development Status :: 2 - Pre-Alpha
Classifier: Framework :: AsyncIO
Classifier: Framework :: OpenTelemetry :: Instrumentations
Classifier: Framework :: Pydantic
Classifier: Framework :: Pytest
Classifier: Intended Audience :: Developers
Classifier: Intended Audience :: End Users/Desktop
Classifier: License :: OSI Approved :: MIT License
Classifier: Natural Language :: English
Classifier: Operating System :: MacOS :: MacOS X
Classifier: Operating System :: Microsoft :: Windows
Classifier: Operating System :: POSIX :: Linux
Classifier: Programming Language :: Python
Classifier: Programming Language :: Python :: 3
Classifier: Programming Language :: Python :: 3.11
Classifier: Programming Language :: Python :: 3.12
Classifier: Programming Language :: Python :: 3.13
Classifier: Typing :: Typed
Requires-Python: <4.0,>=3.11
Requires-Dist: atlassian-python-api>=4.0.0
Requires-Dist: beautifulsoup4>=4.13.3
Requires-Dist: brave-search-python-client>=0.4.9
Requires-Dist: cryptography>=44.0.1
Requires-Dist: email-validator>=2.2.0
Requires-Dist: enum-tools>=0.12.0
Requires-Dist: griffe>=1.7.0
Requires-Dist: logfire[system-metrics]>=3.12.0
Requires-Dist: markdown>=3.7
Requires-Dist: markdownify>=1.0.0
Requires-Dist: markitdown[docx,xlsx]>=0.1.1
Requires-Dist: mcp==1.3.0
Requires-Dist: opentelemetry-api>=1.31.1
Requires-Dist: opentelemetry-instrumentation-httpx>=0.50b0
Requires-Dist: opentelemetry-instrumentation-requests>=0.50b0
Requires-Dist: opentelemetry-instrumentation-sqlite3>=0.50b0
Requires-Dist: opentelemetry-instrumentation-starlette>=0.50b0
Requires-Dist: opentelemetry-instrumentation-urllib3>=0.50b0
Requires-Dist: opentelemetry-instrumentation-urllib>=0.50b0
Requires-Dist: opentelemetry-instrumentation>=0.50b0
Requires-Dist: protego>=0.4.0
Requires-Dist: pydantic-settings>=2.8.1
Requires-Dist: pydantic>=2.11.0
Requires-Dist: pymupdf4llm>=0.0.18
Requires-Dist: pymupdf==1.25.4
Requires-Dist: python-dotenv>=1.1.0
Requires-Dist: readabilipy>=0.3.0
Requires-Dist: sphinx-toolbox>=3.8.3
Requires-Dist: strip-markdown>=1.3
Requires-Dist: typer>=0.15.2
Provides-Extra: examples
Requires-Dist: jinja2>=3.1.6; extra == 'examples'
Requires-Dist: jupyter>=1.1.1; extra == 'examples'
Requires-Dist: marimo>=0.12.2; extra == 'examples'
Requires-Dist: streamlit>=1.44.1; extra == 'examples'
Provides-Extra: imaging
Requires-Dist: cairosvg>=2.7.1; extra == 'imaging'
Requires-Dist: svglib>=1.5.1; extra == 'imaging'
